{"filter":false,"title":"Generation-aligned.json","tooltip":"/configs/Generation-aligned.json","undoManager":{"mark":1,"position":1,"stack":[[{"start":{"row":0,"column":0},"end":{"row":35,"column":0},"action":"insert","lines":["{","  \"deepdive_views\": [","    {","      \"key\": \"Context\",","      \"name\": \"生活文脈\",","      \"detail\": \"行動（Activities）、環境（Environment）、関わり（Interactions）、使用物（Objects）、利用者像（Users）\"","    },","    {","      \"key\": \"Episodes\",","      \"name\": \"具体的な出来事・エピソード\",","      \"detail\": \"典型的一日の流れ、印象的だった瞬間、課題が現れる具体場面\"","    },","    {","      \"key\": \"EmotionsValues\",","      \"name\": \"感情と価値観\",","      \"detail\": \"どこがつらいのか、優先している価値、葛藤や妥協点\"","    },","    {","      \"key\": \"AttemptsBarriers\",","      \"name\": \"対処行動と限界\",","      \"detail\": \"過去に試した工夫、なぜ継続できなかったか、障害となる要因\"","    },","    {","      \"key\": \"IdealState\",","      \"name\": \"理想状態\",","      \"detail\": \"「こうなっていればよい」という状態像。利用者が本当に望む価値\"","    },","    {","      \"key\": \"Extras\",","      \"name\": \"その他の補足情報\",","      \"detail\": \"時間制約、リソース、周囲の影響、利用者固有の事情など\"","    }","  ],","  \"note\": \"観点は固定順序ではなく、必要性に応じて柔軟に扱う\"","}",""],"id":1}],[{"start":{"row":1,"column":3},"end":{"row":1,"column":17},"action":"remove","lines":["deepdive_views"],"id":2},{"start":{"row":1,"column":3},"end":{"row":1,"column":22},"action":"insert","lines":["deepdive_categories"]}]]},"ace":{"folds":[],"scrolltop":120,"scrollleft":0,"selection":{"start":{"row":19,"column":24},"end":{"row":19,"column":24},"isBackwards":false},"options":{"guessTabSize":true,"useWrapMode":false,"wrapToView":true},"firstLineState":0},"timestamp":1769606749711,"hash":"648f91f081a4dc15a20079cd69583e5ffe505a80"}